{"type":"FeatureCollection","features":[{"type":"Feature","properties":{"marker-color":"#7e7e7e","marker-size":"medium","marker-symbol":"","NAME":"Pantai 6","ADDRESS":"Jalan Pantai 6","CITY":"BANGKA","GAMBAR":"Pantai6.jpg"},"geometry":{"type":"Point","coordinates":[106.04827880859375,-1.6127173053796162]}},{"type":"Feature","properties":{"marker-color":"#7e7e7e","marker-size":"medium","marker-symbol":"","NAME":"Pantai 7","ADDRESS":"Jalan Pantai 7","CITY":"BANGKA","GAMBAR":"Pantai7.jpg"},"geometry":{"type":"Point","coordinates":[106.0125732421875,-1.5845757975049797]}},{"type":"Feature","properties":{"marker-color":"#7e7e7e","marker-size":"medium","marker-symbol":"","NAME":"Pantai 9","ADDRESS":"Jalan Pantai 9","CITY":"BANGKA","GAMBAR":"Pantai9.jpg"},"geometry":{"type":"Point","coordinates":[105.9576416015625,-1.5591794741747402]}},{"type":"Feature","properties":{"marker-color":"#7e7e7e","marker-size":"medium","marker-symbol":"","NAME":"Pantai 12","ADDRESS":"Jalan Pantai 12","CITY":"BANGKA","GAMBAR":"Pantai12.jpg"},"geometry":{"type":"Point","coordinates":[105.88623046874999,-1.5166227885284307]}},{"type":"Feature","properties":{"marker-color":"#7e7e7e","marker-size":"medium","marker-symbol":"","NAME":"Pantai 2","ADDRESS":"Jalan Pantai 2","CITY":"BANGKA","GAMBAR":"pantai2.jpg"},"geometry":{"type":"Point","coordinates":[106.04484558105469,-1.7101799646658005]}},{"type":"Feature","properties":{"marker-color":"#7e7e7e","marker-size":"medium","marker-symbol":"","NAME":"Pantai 4","ADDRESS":"Jalan Pantai 4","CITY":"BANGKA","GAMBAR":"Pantai4.jpg"},"geometry":{"type":"Point","coordinates":[106.02287292480469,-1.6710582084456997]}},{"type":"Feature","properties":{"marker-color":"#7e7e7e","marker-size":"medium","marker-symbol":"","NAME":"Pantai 5","ADDRESS":"Jalan Pantai 5","CITY":"BANGKA","GAMBAR":"Pantai5.jpg"},"geometry":{"type":"Point","coordinates":[106.03179931640625,-1.6182082861447993]}},{"type":"Feature","properties":{"marker-color":"#7e7e7e","marker-size":"medium","marker-symbol":"","NAME":"Pantai 8","ADDRESS":"Jalan Pantai 8","CITY":"BANGKA","GAMBAR":"Pantai8.jpg"},"geometry":{"type":"Point","coordinates":[105.99128723144531,-1.5646705972455603]}},{"type":"Feature","properties":{"marker-color":"#7e7e7e","marker-size":"medium","marker-symbol":"","NAME":"Pantai 3","ADDRESS":"Jalan Pantai 3","CITY":"BANGKA","GAMBAR":"Pantai3.jpg"},"geometry":{"type":"Point","coordinates":[106.029052734375,-1.6889033178172674]}},{"type":"Feature","properties":{"marker-color":"#7e7e7e","marker-size":"medium","marker-symbol":"","NAME":"Pantai 11","ADDRESS":"Jalan Pantai 11","CITY":"BANGKA","GAMBAR":"Pantai11.jpg"},"geometry":{"type":"Point","coordinates":[105.91232299804688,-1.5337828444330561]}},{"type":"Feature","properties":{"marker-color":"#7e7e7e","marker-size":"medium","marker-symbol":"","NAME":"Pantai 10","ADDRESS":"Jalan Pantai 10","CITY":"BANGKA","GAMBAR":"Pantai10.jpg"},"geometry":{"type":"Point","coordinates":[105.92605590820312,-1.5488835798473852]}},{"type":"Feature","properties":{"marker-color":"#7e7e7e","marker-size":"medium","marker-symbol":"","NAME":"Pantai 1","ADDRESS":"Jalan Pantai 1","CITY":"BANGKA","GAMBAR":"pantai1.jpg"},"geometry":{"type":"Point","coordinates":[106.05514526367188,-1.7177296860270803]}}]}